unfolded/map_sdk/__init__.py
unfolded/map_sdk/_frontend.py
unfolded/map_sdk/_poll.py
unfolded/map_sdk/_version.py
unfolded/map_sdk/colab.py
unfolded/map_sdk/environment.py
unfolded/map_sdk/errors.py
unfolded/map_sdk/poll.py
unfolded/map_sdk/transfer_utils.py
unfolded/map_sdk/types.py
unfolded/map_sdk/_poll_v56/__init__.py
unfolded/map_sdk/_poll_v56/_async_thread.py
unfolded/map_sdk/_poll_v56/_poll.py
unfolded/map_sdk/_poll_v56/_version.py
unfolded/map_sdk/api/__init__.py
unfolded/map_sdk/api/annotation_api.py
unfolded/map_sdk/api/base.py
unfolded/map_sdk/api/create_map.py
unfolded/map_sdk/api/dataset_api.py
unfolded/map_sdk/api/effect_api.py
unfolded/map_sdk/api/enums.py
unfolded/map_sdk/api/event_api.py
unfolded/map_sdk/api/filter_api.py
unfolded/map_sdk/api/layer_api.py
unfolded/map_sdk/api/map_api.py
unfolded/map_sdk/generated/Annotation.py
unfolded/map_sdk/generated/Chart.py
unfolded/map_sdk/generated/Effect.py
unfolded/map_sdk/generated/Filter.py
unfolded/map_sdk/generated/Layer.py
unfolded/map_sdk/generated/MapState.py
unfolded/map_sdk/labextension/package.json
unfolded/map_sdk/labextension/static/4.42f85ee4eb09414a2077.js
unfolded/map_sdk/labextension/static/4.73146123c848733435f6.js
unfolded/map_sdk/labextension/static/480.a4d2f116692243975697.js
unfolded/map_sdk/labextension/static/568.3358220e8771c6c678ae.js
unfolded/map_sdk/labextension/static/747.7af3ebbfcdb1b88bd23f.js
unfolded/map_sdk/labextension/static/remoteEntry.9f6dff82050d86fb0fd7.js
unfolded/map_sdk/labextension/static/remoteEntry.e752d0576d57a79700f7.js
unfolded/map_sdk/labextension/static/style.js
unfolded/map_sdk/labextension/static/third-party-licenses.json
unfolded/map_sdk/map/__init__.py
unfolded/map_sdk/map/base.py
unfolded/map_sdk/map/html.py
unfolded/map_sdk/map/widget.py
unfolded/map_sdk/nbextension/extension.js
unfolded/map_sdk/nbextension/index.js
unfolded/map_sdk/templates/html_map_sdk.j2
unfolded/map_sdk/transport/__init__.py
unfolded/map_sdk/transport/base.py
unfolded.map_sdk-1.13.0.dist-info/METADATA
unfolded.map_sdk-1.13.0.dist-info/WHEEL
unfolded.map_sdk-1.13.0.dist-info/top_level.txt
unfolded.map_sdk-1.13.0.dist-info/RECORD
